README
setup.py
txoauth/__init__.py
txoauth/_twisted.py
txoauth/_version.py
txoauth/clientcred.py
txoauth/interfaces.py
txoauth/token.py
txoauth.egg-info/PKG-INFO
txoauth.egg-info/SOURCES.txt
txoauth.egg-info/dependency_links.txt
txoauth.egg-info/not-zip-safe
txoauth.egg-info/requires.txt
txoauth.egg-info/top_level.txt
txoauth/contrib/__init__.py
txoauth/contrib/simple.py
txoauth/contrib/test/__init__.py
txoauth/contrib/test/test_simple.py
txoauth/test/__init__.py
txoauth/test/test_clientcred.py
txoauth/test/test_token.py
txoauth/test/test_twisted.py