Metadata-Version: 1.0
Name: txoauth
Version: 1.0.11
Summary: provides OAuth 2.0 support for Twisted.
Home-page: https://github.com/simplegeo/txoauth
Author: Zooko Ofsimplegeo
Author-email: zooko@simplegeo.com
License: BSD
Platform: UNKNOWN
Classifier: Development Status :: 4 - Beta
Classifier: License :: OSI Approved :: BSD License
Classifier: License :: DFSG approved
Classifier: Intended Audience :: Developers
Classifier: Operating System :: OS Independent
Classifier: Natural Language :: English
Classifier: Programming Language :: Python
Classifier: Programming Language :: Python :: 2
Classifier: Programming Language :: Python :: 2.5
Classifier: Programming Language :: Python :: 2.6
Classifier: Topic :: Utilities
Classifier: Topic :: Software Development :: Libraries
